{
    "tournament_participation": {
        "5000000248": {
            "team_id": 5000381095,
            "team_password": true,
            "team_status": "confirmed",
            "stages": {
                "5000000594": {
                    "groups": [
                        5000054928
                    ]
                },
                "5000000593": {
                    "groups": [
                        5000054918
                    ]
                }
            }
        }
    },
    "uuid": 528148230,
    "nickname": "Leev1"
}